topsis_bhavuk_102303140/__init__.py
topsis_bhavuk_102303140/topsis.py
topsis_bhavuk_102303140-0.0.4.dist-info/METADATA
topsis_bhavuk_102303140-0.0.4.dist-info/WHEEL
topsis_bhavuk_102303140-0.0.4.dist-info/entry_points.txt
topsis_bhavuk_102303140-0.0.4.dist-info/top_level.txt
topsis_bhavuk_102303140-0.0.4.dist-info/RECORD
