Metadata-Version: 2.4
Name: Topsis-Bhavuk-102303140
Version: 0.0.4
Summary: TOPSIS package for MCDM problems
Author: Bhavuk Mahajan
Author-email: bhavukmahajan007@gmail.com
License: MIT
Requires-Python: >=3.6
Requires-Dist: numpy
Requires-Dist: pandas
Dynamic: author
Dynamic: author-email
Dynamic: description
Dynamic: description-content-type
Dynamic: license
Dynamic: requires-dist
Dynamic: requires-python
Dynamic: summary
